{
    "paths": {},
    "uuids": [
        "004u4x2P5MjYuNoQMjh7FZ",
        "02delMVqdBD70a/HSD99FK",
        "0cngrFPwZDGaljzLNlNr20",
        "15LfQs79BMj4KWpg73lo5m",
        "18dfJZpupJ2Z8bDMYaHrFP",
        "1bLJfYkZNO0bBPN77dgt//",
        "20zTpsEglMP7X1MyadNow2",
        "21SZAu+k9CbJe61rUmWiJ+",
        "225uzcKVRP8pycwRznemdO",
        "28l3ycu8RG4atXIuD084uX",
        "29FYIk+N1GYaeWH/q1NxQO",
        "2dL3kvpAxJu6GJ7RdqJG5J",
        "2dynEV/d9OzaXYKBUkFo42",
        "34B4qnYl5CnqsTWywpKgDB",
        "35EzlSoRJLhJ5EgQtgoxBQ",
        "35KSZb8GlNu7ouetEbZe3K",
        "42xmQSEhhD7pCyaL0xN7jQ",
        "49dOKzmZxAo7AwlLcUZdCp",
        "52g/6yMRdPQZjXvtrUwdww",
        "63qFFlxAxKZ5tJD8xPtkmO",
        "684IrCwYRFNKHf5nHYlo0B",
        "695QVHH1hPO4Gm5y9/pw8I",
        "6eBWFz0oVHPLIGQKf/9Thu",
        "71VhFCTINJM6/Ky3oX9nBT",
        "8bKyfyOgpD1rnmCyQURifB",
        "8cLxxCoz5LWbjEhlKBn71W",
        "8c20Sso/ZEn7NUfNSM+EBh",
        "8fHANwGm9FF5TjSthRbS79",
        "95clhfYM1Oaqixi57B7biF",
        "a0K3OR3ghDLYl3YW1eQiRp",
        "a04yeCJ2lJxobwBjSy3B2y",
        "a2MjXRFdtLlYQ5ouAFv/+R",
        "a6ZHxgSrlFk4ChdJ1I/vB2",
        "a9KrXUmqREEaO9rk3wF/PR",
        "b1bNMAdK9C74psdUURMwwb",
        "b4P/PCArtIdIH38t6mlw8Y",
        "bd0t6PlO5OcozNnSQmR6aQ",
        "c22zozzgJCuLejgQ/6Rnbk",
        "cbMUnUEGdMgbzXtiLyHczW",
        "e5YXepd31JbJkFWGuHc2H1",
        "e7hxY5cB9C263RzurTNXpO",
        "e8Ueib+qJEhL6mXAHdnwbi",
        "e9y51mBXVGMoLvVVFOHnfI",
        "e97GVMl6JHh5Ml5qEDdSGa",
        "ecpdLyjvZBwrvm+cedCcQy",
        "f0BIwQ8D5Ml7nTNQbh1YlS",
        "f02w2JIcJAkrm5Q7OnzaNB",
        "fdGk/ox2JLlJR8lDzH5vPz"
    ],
    "scenes": {
        "db://assets/Scene/game.fire": "a6ZHxgSrlFk4ChdJ1I/vB2",
        "db://assets/Scene/start.fire": "2dL3kvpAxJu6GJ7RdqJG5J"
    },
    "redirect": [
        "02delMVqdBD70a/HSD99FK",
        0,
        "ecpdLyjvZBwrvm+cedCcQy",
        0
    ],
    "deps": [
        "internal"
    ],
    "packs": {
        "04d64fb2e": [
            "0cngrFPwZDGaljzLNlNr20",
            "15LfQs79BMj4KWpg73lo5m",
            "18dfJZpupJ2Z8bDMYaHrFP",
            "20zTpsEglMP7X1MyadNow2",
            "21SZAu+k9CbJe61rUmWiJ+",
            "225uzcKVRP8pycwRznemdO",
            "28l3ycu8RG4atXIuD084uX",
            "29FYIk+N1GYaeWH/q1NxQO",
            "2dynEV/d9OzaXYKBUkFo42",
            "52g/6yMRdPQZjXvtrUwdww",
            "695QVHH1hPO4Gm5y9/pw8I",
            "8bKyfyOgpD1rnmCyQURifB",
            "8c20Sso/ZEn7NUfNSM+EBh",
            "95clhfYM1Oaqixi57B7biF",
            "a0K3OR3ghDLYl3YW1eQiRp",
            "a04yeCJ2lJxobwBjSy3B2y",
            "a2MjXRFdtLlYQ5ouAFv/+R",
            "a6ZHxgSrlFk4ChdJ1I/vB2",
            "c22zozzgJCuLejgQ/6Rnbk",
            "cbMUnUEGdMgbzXtiLyHczW",
            "e5YXepd31JbJkFWGuHc2H1",
            "e97GVMl6JHh5Ml5qEDdSGa",
            "f0BIwQ8D5Ml7nTNQbh1YlS"
        ],
        "055cd4a19": [
            "34B4qnYl5CnqsTWywpKgDB",
            "35EzlSoRJLhJ5EgQtgoxBQ",
            "42xmQSEhhD7pCyaL0xN7jQ",
            "49dOKzmZxAo7AwlLcUZdCp",
            "63qFFlxAxKZ5tJD8xPtkmO",
            "684IrCwYRFNKHf5nHYlo0B",
            "6eBWFz0oVHPLIGQKf/9Thu",
            "71VhFCTINJM6/Ky3oX9nBT",
            "8cLxxCoz5LWbjEhlKBn71W",
            "8fHANwGm9FF5TjSthRbS79",
            "b1bNMAdK9C74psdUURMwwb",
            "b4P/PCArtIdIH38t6mlw8Y",
            "bd0t6PlO5OcozNnSQmR6aQ",
            "e7hxY5cB9C263RzurTNXpO",
            "e8Ueib+qJEhL6mXAHdnwbi",
            "e9y51mBXVGMoLvVVFOHnfI",
            "fdGk/ox2JLlJR8lDzH5vPz"
        ],
        "05b545b3a": [
            "004u4x2P5MjYuNoQMjh7FZ",
            "1bLJfYkZNO0bBPN77dgt//",
            "35KSZb8GlNu7ouetEbZe3K",
            "a9KrXUmqREEaO9rk3wF/PR",
            "f02w2JIcJAkrm5Q7OnzaNB"
        ],
        "06bd28ff9": [
            "004u4x2P5MjYuNoQMjh7FZ",
            "29FYIk+N1GYaeWH/q1NxQO",
            "2dL3kvpAxJu6GJ7RdqJG5J",
            "a2MjXRFdtLlYQ5ouAFv/+R",
            "e97GVMl6JHh5Ml5qEDdSGa",
            "f0BIwQ8D5Ml7nTNQbh1YlS"
        ]
    },
    "name": "main",
    "importBase": "import",
    "nativeBase": "native",
    "debug": true,
    "isZip": false,
    "encrypted": false,
    "versions": {
        "import": [
            "04d64fb2e",
            "40353",
            "055cd4a19",
            "e0132",
            "05b545b3a",
            "253ba",
            "06bd28ff9",
            "b019a"
        ],
        "native": [
            "0cngrFPwZDGaljzLNlNr20",
            "ac0a1",
            "28l3ycu8RG4atXIuD084uX",
            "d681d",
            "34B4qnYl5CnqsTWywpKgDB",
            "d829e",
            "35EzlSoRJLhJ5EgQtgoxBQ",
            "688f8",
            "35KSZb8GlNu7ouetEbZe3K",
            "5ddce",
            "42xmQSEhhD7pCyaL0xN7jQ",
            "eeca7",
            "49dOKzmZxAo7AwlLcUZdCp",
            "a56cb",
            "63qFFlxAxKZ5tJD8xPtkmO",
            "82cf2",
            "684IrCwYRFNKHf5nHYlo0B",
            "45540",
            "6eBWFz0oVHPLIGQKf/9Thu",
            "6d3cf",
            "71VhFCTINJM6/Ky3oX9nBT",
            "c06a9",
            "8cLxxCoz5LWbjEhlKBn71W",
            "834f4",
            "8fHANwGm9FF5TjSthRbS79",
            "c5541",
            "b1bNMAdK9C74psdUURMwwb",
            "8e54f",
            "b4P/PCArtIdIH38t6mlw8Y",
            "83fcc",
            "bd0t6PlO5OcozNnSQmR6aQ",
            "c5f89",
            "e7hxY5cB9C263RzurTNXpO",
            "e1c7f",
            "e8Ueib+qJEhL6mXAHdnwbi",
            "90cf4",
            "e9y51mBXVGMoLvVVFOHnfI",
            "512fe",
            "fdGk/ox2JLlJR8lDzH5vPz",
            "b1932"
        ]
    }
}